aleatory/__init__.py
aleatory/processes/__init__.py
aleatory/processes/base.py
aleatory/processes/base_analytical.py
aleatory/processes/base_eu.py
aleatory/processes/analytical/__init__.py
aleatory/processes/analytical/bes.py
aleatory/processes/analytical/besq.py
aleatory/processes/analytical/brownian_bridge.py
aleatory/processes/analytical/brownian_excursion.py
aleatory/processes/analytical/brownian_meander.py
aleatory/processes/analytical/brownian_motion.py
aleatory/processes/analytical/gaussian.py
aleatory/processes/analytical/geometric_brownian.py
aleatory/processes/analytical/increments.py
aleatory/processes/euler_maruyama/__init__.py
aleatory/processes/euler_maruyama/cev_process.py
aleatory/processes/euler_maruyama/cir_process.py
aleatory/processes/euler_maruyama/ckls_process.py
aleatory/processes/euler_maruyama/ckls_process_generic.py
aleatory/processes/euler_maruyama/ornstein_uhlenbeck.py
aleatory/processes/euler_maruyama/vasicek.py
aleatory/processes/fractional/__init__.py
aleatory/processes/fractional/fbm.py
aleatory/processes/jump/__init__.py
aleatory/processes/jump/galton_watson.py
aleatory/processes/jump/gamma.py
aleatory/processes/jump/gen_random_walk.py
aleatory/processes/jump/hawkes.py
aleatory/processes/jump/inverse_gaussian.py
aleatory/processes/jump/poisson.py
aleatory/processes/jump/poisson_mixed.py
aleatory/processes/jump/poisson_nonhomogeneous.py
aleatory/processes/jump/random_walk.py
aleatory/processes/jump/variance_gamma.py
aleatory/processes/multi_dimensional/brownian_motion_2d.py
aleatory/processes/multi_dimensional/brownian_motion_multi.py
aleatory/processes/multi_dimensional/random_walk_2d.py
aleatory/processes/multi_dimensional/two_correlated_brownian_motions.py
aleatory/stats/__init__.py
aleatory/stats/non_central_chi.py
aleatory/stats/variance_gamma.py
aleatory/styles/__init__.py
aleatory/styles/quant-pastel-light.mplstyle
aleatory/styles/quant_pastel.py
aleatory/utils/__init__.py
aleatory/utils/plotters.py
aleatory-1.1.1.dist-info/licenses/LICENSE
aleatory-1.1.1.dist-info/METADATA
aleatory-1.1.1.dist-info/WHEEL
aleatory-1.1.1.dist-info/top_level.txt
aleatory-1.1.1.dist-info/RECORD
