Metadata-Version: 2.4
Name: aleatory
Version: 1.1.1
Summary: Stochastic Processes Simulation and Visualisation
Author-email: Dialid Santiago <d.santiago@outlook.com>
Project-URL: Homepage, https://github.com/quantgirluk/aleatory
Project-URL: Bug Tracker, https://github.com/quantgirluk/aleatory/issues
Project-URL: Documentation, https://aleatory.readthedocs.io/en/latest/
Classifier: Programming Language :: Python :: 3
Classifier: License :: OSI Approved :: MIT License
Classifier: Operating System :: OS Independent
Classifier: Topic :: Scientific/Engineering :: Mathematics
Classifier: Topic :: Scientific/Engineering :: Visualization
Requires-Python: >=3.8
License-File: LICENSE
Requires-Dist: pandas>=1.5.2
Requires-Dist: numpy>=1.23.5
Requires-Dist: scipy>=1.9.3
Requires-Dist: matplotlib>=3.6.2
Requires-Dist: statsmodels>=0.13.5
Requires-Dist: parameterized>=0.8.1
Dynamic: license-file
